_pyaprwrapper.cpython-311-darwin.so
pyapr/_version.py
pyapr/_common.py
pyapr/__init__.py
pyapr/tree/fill_tree.py
pyapr/tree/__init__.py
pyapr/tree/tree_ops.py
pyapr/restoration/__init__.py
pyapr/restoration/richardson_lucy.py
pyapr/converter/converter_methods.py
pyapr/converter/__init__.py
pyapr/segmentation/__init__.py
pyapr/segmentation/graphcut.py
pyapr/io/__init__.py
pyapr/io/io_api.py
pyapr/tests/test_utils.py
pyapr/tests/test_transform.py
pyapr/tests/test_segmentation.py
pyapr/tests/test_tree.py
pyapr/tests/test_measure.py
pyapr/tests/test_filter.py
pyapr/tests/test_morphology.py
pyapr/tests/__init__.py
pyapr/tests/test_io.py
pyapr/tests/test_gui.py
pyapr/tests/test_restoration.py
pyapr/tests/test_particledata.py
pyapr/tests/test_converter.py
pyapr/tests/test_iterator.py
pyapr/tests/helpers.py
pyapr/tests/test_reconstruction.py
pyapr/utils/filegui.py
pyapr/utils/__init__.py
pyapr/utils/types.py
pyapr/.dylibs/libomp.dylib
pyapr/.dylibs/libhdf5.310.dylib
pyapr/.dylibs/libsz.2.0.1.dylib
pyapr/.dylibs/liblzma.5.dylib
pyapr/.dylibs/libjpeg.8.3.2.dylib
pyapr/.dylibs/libblosc.1.21.5.dylib
pyapr/.dylibs/libzstd.1.5.5.dylib
pyapr/.dylibs/libtiff.6.dylib
pyapr/viewer/compressInteractive.py
pyapr/viewer/__init__.py
pyapr/viewer/partsViewer.py
pyapr/viewer/particleScatterPlot.py
pyapr/viewer/raycastViewer.py
pyapr/measure/_find_objects.py
pyapr/measure/__init__.py
pyapr/measure/_find_label_centers.py
pyapr/measure/_find_label_volume.py
pyapr/measure/_connected_component.py
pyapr/morphology/__init__.py
pyapr/morphology/morphology.py
pyapr/reconstruction/APRSlicer.py
pyapr/reconstruction/__init__.py
pyapr/reconstruction/LazySlicer.py
pyapr/reconstruction/reconstruct.py
pyapr/filter/convolution.py
pyapr/filter/gradient.py
pyapr/filter/std.py
pyapr/filter/__init__.py
pyapr/filter/rank_filters.py
pyapr/filter/stencils.py
pyapr/transform/__init__.py
pyapr/transform/projection.py
pyapr-1.0.7.dist-info/RECORD
pyapr-1.0.7.dist-info/LICENSE
pyapr-1.0.7.dist-info/WHEEL
pyapr-1.0.7.dist-info/top_level.txt
pyapr-1.0.7.dist-info/METADATA
