Metadata-Version: 2.1
Name: pyapr
Version: 1.0.7
Summary: Content-adaptive image processing using the Adaptive Particle Representation
Home-page: https://github.com/AdaptiveParticles/pyapr
Author: Joel Jonsson, Bevan Cheeseman
Author-email: jonsson@mpi-cbg.de
License: Apache-2.0
Classifier: Development Status :: 4 - Beta
Classifier: Intended Audience :: Developers
Classifier: License :: OSI Approved :: Apache Software License
Classifier: Programming Language :: Python :: 3
Classifier: Programming Language :: Python :: 3.8
Classifier: Programming Language :: Python :: 3.9
Classifier: Programming Language :: Python :: 3.10
Classifier: Programming Language :: Python :: 3.11
Classifier: Topic :: Scientific/Engineering
Classifier: Topic :: Scientific/Engineering :: Image Processing
License-File: LICENSE
Requires-Dist: numpy
Requires-Dist: scikit-image
Requires-Dist: PyQt5
Requires-Dist: pyqtgraph
Requires-Dist: tifffile
Requires-Dist: matplotlib
